.DS_Store
pickprimes/__init__.py
pickprimes-2.2.dist-info/LICENSE
pickprimes-2.2.dist-info/METADATA
pickprimes-2.2.dist-info/WHEEL
pickprimes-2.2.dist-info/top_level.txt
pickprimes-2.2.dist-info/RECORD
