Metadata-Version: 2.1
Name: pickprimes
Version: 2.2
Summary: A tool to pick prime numbers between 1 and n and to indicate whether an integer is prime or not
Author: Marcial Mosqueda
Author-email: marcial.mosqueda@gmail.com
License: GNU GPLv3
Keywords: pickprimes prime numbers
Platform: UNKNOWN
Classifier: Development Status :: 4 - Beta
Classifier: Intended Audience :: Developers
Classifier: Topic :: Utilities
Classifier: License :: OSI Approved :: GNU General Public License v3 (GPLv3)
Classifier: Programming Language :: Python :: 3
Classifier: Operating System :: OS Independent
License-File: LICENSE
